<?xml version="1.0" encoding="UTF-8"?>
<csw:GetRecordByIdResponse xmlns:csw="http://www.opengis.net/cat/csw/2.0.2">
  <gmd:MD_Metadata xmlns:gmd="http://www.isotc211.org/2005/gmd" xmlns:gsr="http://www.isotc211.org/2005/gsr" xmlns:gco="http://www.isotc211.org/2005/gco" xmlns:gmx="http://www.isotc211.org/2005/gmx" xmlns:xs="http://www.w3.org/2001/XMLSchema" xmlns:gml="http://www.opengis.net/gml" xmlns:xsi="http://www.w3.org/2001/XMLSchema-instance" xmlns:gts="http://www.isotc211.org/2005/gts" xmlns:srv="http://www.isotc211.org/2005/srv" xmlns:geonet="http://www.fao.org/geonetwork" xsi:schemaLocation="http://www.isotc211.org/2005/gmd http://schemas.opengis.net/iso/19139/20060504/gmd/gmd.xsd http://www.isotc211.org/2005/gmx http://schemas.opengis.net/iso/19139/20060504/gmx/gmx.xsd">
    <gmd:fileIdentifier>
      <gco:CharacterString>bb11be63-bd38-4632-bf54-df44c423a529</gco:CharacterString>
    </gmd:fileIdentifier>
    <gmd:language>
      <gmd:LanguageCode codeList="http://www.loc.gov/standards/iso639-2/" codeListValue="dut">Nederlands; Vlaams</gmd:LanguageCode>
    </gmd:language>
    <gmd:hierarchyLevel>
      <gmd:MD_ScopeCode codeList="http://standards.iso.org/ittf/PubliclyAvailableStandards/ISO_19139_Schemas/resources/codelist/ML_gmxCodelists.xml#MD_ScopeCode" codeListValue="dataset">dataset</gmd:MD_ScopeCode>
    </gmd:hierarchyLevel>
    <gmd:contact>
      <gmd:CI_ResponsibleParty>
        <gmd:individualName gco:nilReason="missing">
          <gco:CharacterString />
        </gmd:individualName>
        <gmd:organisationName>
          <gco:CharacterString>Ministerie van Defensie, Koninklijke Marine, Dienst der Hydrografie</gco:CharacterString>
        </gmd:organisationName>
        <gmd:positionName>
          <gco:CharacterString>Hoofd Gegevens Beheer</gco:CharacterString>
        </gmd:positionName>
        <gmd:contactInfo>
          <gmd:CI_Contact>
            <gmd:phone>
              <gmd:CI_Telephone>
                <gmd:voice gco:nilReason="missing">
                  <gco:CharacterString />
                </gmd:voice>
                <gmd:facsimile gco:nilReason="missing">
                  <gco:CharacterString />
                </gmd:facsimile>
              </gmd:CI_Telephone>
            </gmd:phone>
            <gmd:address>
              <gmd:CI_Address>
                <gmd:deliveryPoint gco:nilReason="missing">
                  <gco:CharacterString />
                </gmd:deliveryPoint>
                <gmd:city gco:nilReason="missing">
                  <gco:CharacterString />
                </gmd:city>
                <gmd:administrativeArea gco:nilReason="missing">
                  <gco:CharacterString />
                </gmd:administrativeArea>
                <gmd:postalCode gco:nilReason="missing">
                  <gco:CharacterString />
                </gmd:postalCode>
                <gmd:country gco:nilReason="missing">
                  <gco:CharacterString />
                </gmd:country>
                <gmd:electronicMailAddress>
                  <gco:CharacterString>data@hydro.nl</gco:CharacterString>
                </gmd:electronicMailAddress>
              </gmd:CI_Address>
            </gmd:address>
            <gmd:onlineResource>
              <gmd:CI_OnlineResource>
                <gmd:linkage>
                  <gmd:URL>www.hydro.nl</gmd:URL>
                </gmd:linkage>
              </gmd:CI_OnlineResource>
            </gmd:onlineResource>
          </gmd:CI_Contact>
        </gmd:contactInfo>
        <gmd:role>
          <gmd:CI_RoleCode codeList="http://standards.iso.org/ittf/PubliclyAvailableStandards/ISO_19139_Schemas/resources/codelist/ML_gmxCodelists.xml#CI_RoleCode" codeListValue="pointOfContact">contactpunt</gmd:CI_RoleCode>
        </gmd:role>
      </gmd:CI_ResponsibleParty>
    </gmd:contact>
    <gmd:dateStamp>
      <gco:Date>2019-12-13</gco:Date>
    </gmd:dateStamp>
    <gmd:metadataStandardName>
      <gco:CharacterString>ISO 19115</gco:CharacterString>
    </gmd:metadataStandardName>
    <gmd:metadataStandardVersion>
      <gco:CharacterString>Nederlands metadata profiel op ISO 19115 voor geografie 2.0</gco:CharacterString>
    </gmd:metadataStandardVersion>
    <gmd:referenceSystemInfo>
      <gmd:MD_ReferenceSystem>
        <gmd:referenceSystemIdentifier>
          <gmd:RS_Identifier>
            <gmd:code>
              <gmx:Anchor xmlns:xlink="http://www.w3.org/1999/xlink" xlink:href="http://www.opengis.net/def/crs/EPSG/0/https://www.opengis.net/def/crs/EPSG/0/4258">https://www.opengis.net/def/crs/EPSG/0/4258</gmx:Anchor>
            </gmd:code>
          </gmd:RS_Identifier>
        </gmd:referenceSystemIdentifier>
      </gmd:MD_ReferenceSystem>
    </gmd:referenceSystemInfo>
    <gmd:identificationInfo>
      <gmd:MD_DataIdentification>
        <gmd:citation>
          <gmd:CI_Citation>
            <gmd:title>
              <gco:CharacterString>Territoriale Zee volgens UNCLOS - Noordzee</gco:CharacterString>
            </gmd:title>
            <gmd:date>
              <gmd:CI_Date>
                <gmd:date>
                  <gco:Date>2009-03-13</gco:Date>
                </gmd:date>
                <gmd:dateType>
                  <gmd:CI_DateTypeCode codeListValue="creation" codeList="http://standards.iso.org/ittf/PubliclyAvailableStandards/ISO_19139_Schemas/resources/codelist/ML_gmxCodelists.xml#CI_DateTypeCode">creatie</gmd:CI_DateTypeCode>
                </gmd:dateType>
              </gmd:CI_Date>
            </gmd:date>
            <gmd:identifier>
              <gmd:MD_Identifier>
                <gmd:code>
                  <gmx:Anchor xmlns:xlink="http://www.w3.org/1999/xlink" xlink:href="https://www.nationaalgeoregister.nl/geonetwork/srv/api/recordsbb11be63-bd38-4632-bf54-df44c423a529">bb11be63-bd38-4632-bf54-df44c423a529</gmx:Anchor>
                </gmd:code>
              </gmd:MD_Identifier>
            </gmd:identifier>
          </gmd:CI_Citation>
        </gmd:citation>
        <gmd:abstract>
          <gco:CharacterString>Territoriale Zee van Nederland</gco:CharacterString>
        </gmd:abstract>
        <gmd:purpose gco:nilReason="missing">
          <gco:CharacterString />
        </gmd:purpose>
        <gmd:status>
          <gmd:MD_ProgressCode codeListValue="onGoing" codeList="http://standards.iso.org/ittf/PubliclyAvailableStandards/ISO_19139_Schemas/resources/codelist/ML_gmxCodelists.xml#MD_ProgressCode">continu geactualiseerd</gmd:MD_ProgressCode>
        </gmd:status>
        <gmd:pointOfContact>
          <gmd:CI_ResponsibleParty>
            <gmd:individualName gco:nilReason="missing">
              <gco:CharacterString />
            </gmd:individualName>
            <gmd:organisationName>
              <gco:CharacterString>Ministerie van Defensie, Koninklijke Marine, Dienst der Hydrografie</gco:CharacterString>
            </gmd:organisationName>
            <gmd:positionName>
              <gco:CharacterString>Hoofd Gegevens Beheer</gco:CharacterString>
            </gmd:positionName>
            <gmd:contactInfo>
              <gmd:CI_Contact>
                <gmd:phone>
                  <gmd:CI_Telephone>
                    <gmd:voice gco:nilReason="missing">
                      <gco:CharacterString />
                    </gmd:voice>
                    <gmd:facsimile gco:nilReason="missing">
                      <gco:CharacterString />
                    </gmd:facsimile>
                  </gmd:CI_Telephone>
                </gmd:phone>
                <gmd:address>
                  <gmd:CI_Address>
                    <gmd:deliveryPoint gco:nilReason="missing">
                      <gco:CharacterString />
                    </gmd:deliveryPoint>
                    <gmd:city gco:nilReason="missing">
                      <gco:CharacterString />
                    </gmd:city>
                    <gmd:administrativeArea gco:nilReason="missing">
                      <gco:CharacterString />
                    </gmd:administrativeArea>
                    <gmd:postalCode gco:nilReason="missing">
                      <gco:CharacterString />
                    </gmd:postalCode>
                    <gmd:country gco:nilReason="missing">
                      <gco:CharacterString />
                    </gmd:country>
                    <gmd:electronicMailAddress>
                      <gco:CharacterString>data@hydro.nl</gco:CharacterString>
                    </gmd:electronicMailAddress>
                  </gmd:CI_Address>
                </gmd:address>
                <gmd:onlineResource>
                  <gmd:CI_OnlineResource>
                    <gmd:linkage>
                      <gmd:URL>www.hydro.nl</gmd:URL>
                    </gmd:linkage>
                  </gmd:CI_OnlineResource>
                </gmd:onlineResource>
              </gmd:CI_Contact>
            </gmd:contactInfo>
            <gmd:role>
              <gmd:CI_RoleCode codeList="http://standards.iso.org/ittf/PubliclyAvailableStandards/ISO_19139_Schemas/resources/codelist/ML_gmxCodelists.xml#CI_RoleCode" codeListValue="pointOfContact">contactpunt</gmd:CI_RoleCode>
            </gmd:role>
          </gmd:CI_ResponsibleParty>
        </gmd:pointOfContact>
        <gmd:resourceMaintenance>
          <gmd:MD_MaintenanceInformation>
            <gmd:maintenanceAndUpdateFrequency>
              <gmd:MD_MaintenanceFrequencyCode codeList="http://standards.iso.org/ittf/PubliclyAvailableStandards/ISO_19139_Schemas/resources/codelist/ML_gmxCodelists.xml#MD_MaintenanceFrequencyCode" codeListValue="biannually">1 x per half jaar</gmd:MD_MaintenanceFrequencyCode>
            </gmd:maintenanceAndUpdateFrequency>
            <gmd:dateOfNextUpdate>
              <gco:Date>2099-01-01</gco:Date>
            </gmd:dateOfNextUpdate>
          </gmd:MD_MaintenanceInformation>
        </gmd:resourceMaintenance>
        <gmd:descriptiveKeywords>
          <gmd:MD_Keywords>
            <gmd:keyword>
              <gmx:Anchor xmlns:xlink="http://www.w3.org/1999/xlink" xlink:href="http://www.eionet.europa.eu/gemet/nl/inspire-theme/au">Administratieve eenheden</gmx:Anchor>
            </gmd:keyword>
            <gmd:type>
              <gmd:MD_KeywordTypeCode codeList="http://standards.iso.org/ittf/PubliclyAvailableStandards/ISO_19139_Schemas/resources/codelist/ML_gmxCodelists.xml#MD_KeywordTypeCode" codeListValue="theme">theme</gmd:MD_KeywordTypeCode>
            </gmd:type>
            <gmd:thesaurusName>
              <gmd:CI_Citation>
                <gmd:title>
                  <gmx:Anchor xmlns:xlink="http://www.w3.org/1999/xlink" xlink:href="http://www.eionet.europa.eu/gemet/inspire_themes">GEMET - INSPIRE themes, version 1.0</gmx:Anchor>
                </gmd:title>
                <gmd:date>
                  <gmd:CI_Date>
                    <gmd:date>
                      <gco:Date>2008-06-01</gco:Date>
                    </gmd:date>
                    <gmd:dateType>
                      <gmd:CI_DateTypeCode codeList="http://standards.iso.org/ittf/PubliclyAvailableStandards/ISO_19139_Schemas/resources/codelist/ML_gmxCodelists.xml#CI_DateTypeCode" codeListValue="publication">publicatie</gmd:CI_DateTypeCode>
                    </gmd:dateType>
                  </gmd:CI_Date>
                </gmd:date>
                <gmd:identifier>
                  <gmd:MD_Identifier>
                    <gmd:code>
                      <gmx:Anchor xmlns:xlink="http://www.w3.org/1999/xlink" xlink:href="https://www.nationaalgeoregister.nl:443/geonetwork/srv/eng/thesaurus.download?ref=external.theme.httpinspireeceuropaeutheme-theme">geonetwork.thesaurus.external.theme.httpinspireeceuropaeutheme-theme</gmx:Anchor>
                    </gmd:code>
                  </gmd:MD_Identifier>
                </gmd:identifier>
              </gmd:CI_Citation>
            </gmd:thesaurusName>
          </gmd:MD_Keywords>
        </gmd:descriptiveKeywords>
        <gmd:descriptiveKeywords>
          <gmd:MD_Keywords>
            <gmd:keyword>
              <gco:CharacterString>Territoriale Zee</gco:CharacterString>
            </gmd:keyword>
          </gmd:MD_Keywords>
        </gmd:descriptiveKeywords>
        <gmd:descriptiveKeywords>
          <gmd:MD_Keywords>
            <gmd:keyword>
              <gmx:Anchor xmlns:xlink="http://www.w3.org/1999/xlink" xlink:href="http://inspire.ec.europa.eu/metadata-codelist/SpatialScope/national">Nationaal</gmx:Anchor>
            </gmd:keyword>
            <gmd:type>
              <gmd:MD_KeywordTypeCode codeList="http://standards.iso.org/ittf/PubliclyAvailableStandards/ISO_19139_Schemas/resources/codelist/ML_gmxCodelists.xml#MD_KeywordTypeCode" codeListValue="theme">theme</gmd:MD_KeywordTypeCode>
            </gmd:type>
            <gmd:thesaurusName>
              <gmd:CI_Citation>
                <gmd:title>
                  <gmx:Anchor xmlns:xlink="http://www.w3.org/1999/xlink" xlink:href="http://inspire.ec.europa.eu/metadata-codelist/SpatialScope">Ruimtelijke dekking</gmx:Anchor>
                </gmd:title>
                <gmd:date>
                  <gmd:CI_Date>
                    <gmd:date>
                      <gco:Date>2018-04-04</gco:Date>
                    </gmd:date>
                    <gmd:dateType>
                      <gmd:CI_DateTypeCode codeList="http://standards.iso.org/ittf/PubliclyAvailableStandards/ISO_19139_Schemas/resources/codelist/ML_gmxCodelists.xml#CI_DateTypeCode" codeListValue="publication">publicatie</gmd:CI_DateTypeCode>
                    </gmd:dateType>
                  </gmd:CI_Date>
                </gmd:date>
                <gmd:identifier>
                  <gmd:MD_Identifier>
                    <gmd:code>
                      <gmx:Anchor xmlns:xlink="http://www.w3.org/1999/xlink" xlink:href="https://www.nationaalgeoregister.nl:443/geonetwork/srv/eng/thesaurus.download?ref=external.theme.httpinspireeceuropaeumetadatacodelistSpatialScope-SpatialScope">geonetwork.thesaurus.external.theme.httpinspireeceuropaeumetadatacodelistSpatialScope-SpatialScope</gmx:Anchor>
                    </gmd:code>
                  </gmd:MD_Identifier>
                </gmd:identifier>
              </gmd:CI_Citation>
            </gmd:thesaurusName>
          </gmd:MD_Keywords>
        </gmd:descriptiveKeywords>
        <gmd:resourceSpecificUsage>
          <gmd:MD_Usage>
            <gmd:specificUsage gco:nilReason="missing">
              <gco:CharacterString />
            </gmd:specificUsage>
            <gmd:userContactInfo />
          </gmd:MD_Usage>
        </gmd:resourceSpecificUsage>
        <gmd:resourceConstraints>
          <gmd:MD_Constraints>
            <gmd:useLimitation>
              <gco:CharacterString>De verstrekte gegevens mogen niet gebruikt worden als middel om mee te navigeren, aangezien zij op zichzelf staan en niet bijgewerkt zijn conform de Berichten aan Zeevarenden.</gco:CharacterString>
            </gmd:useLimitation>
            <gmd:useLimitation>
              <gco:CharacterString>De Dienst der Hydrografie behoudt zich het recht voor haar Morele rechten (art. 6 bis Conventie van Bern) uit te oefenen op het gereproduceerde materiaal, waarin de verstrekte gegevens verwerkt zijn.</gco:CharacterString>
            </gmd:useLimitation>
          </gmd:MD_Constraints>
        </gmd:resourceConstraints>
        <gmd:resourceConstraints>
          <gmd:MD_LegalConstraints>
            <gmd:accessConstraints>
              <gmd:MD_RestrictionCode codeListValue="otherRestrictions" codeList="http://standards.iso.org/ittf/PubliclyAvailableStandards/ISO_19139_Schemas/resources/codelist/ML_gmxCodelists.xml#MD_RestrictionCode">anders</gmd:MD_RestrictionCode>
            </gmd:accessConstraints>
            <gmd:otherConstraints>
              <gmx:Anchor xmlns:xlink="http://www.w3.org/1999/xlink" xlink:href="http://creativecommons.org/publicdomain/mark/1.0/deed.nl">Geen beperkingen</gmx:Anchor>
            </gmd:otherConstraints>
            <gmd:otherConstraints>
              <gmx:Anchor xmlns:xlink="http://www.w3.org/1999/xlink" xlink:href="http://inspire.ec.europa.eu/metadata-codelist/ConditionsApplyingToAccessAndUse/noConditionsApply">Er zijn geen condities voor toegang en gebruik</gmx:Anchor>
            </gmd:otherConstraints>
          </gmd:MD_LegalConstraints>
        </gmd:resourceConstraints>
        <gmd:resourceConstraints>
          <gmd:MD_LegalConstraints>
            <gmd:accessConstraints>
              <gmd:MD_RestrictionCode codeListValue="otherRestrictions" codeList="http://standards.iso.org/ittf/PubliclyAvailableStandards/ISO_19139_Schemas/resources/codelist/ML_gmxCodelists.xml#MD_RestrictionCode">anders</gmd:MD_RestrictionCode>
            </gmd:accessConstraints>
            <gmd:otherConstraints>
              <gmx:Anchor xmlns:xlink="http://www.w3.org/1999/xlink" xlink:href="http://inspire.ec.europa.eu/metadata-codelist/LimitationsOnPublicAccess/noLimitations">Geen beperkingen voor publieke toegang</gmx:Anchor>
            </gmd:otherConstraints>
          </gmd:MD_LegalConstraints>
        </gmd:resourceConstraints>
        <gmd:resourceConstraints>
          <gmd:MD_SecurityConstraints>
            <gmd:classification>
              <gmd:MD_ClassificationCode codeList="http://standards.iso.org/ittf/PubliclyAvailableStandards/ISO_19139_Schemas/resources/codelist/ML_gmxCodelists.xml#MD_ClassificationCode" codeListValue="" />
            </gmd:classification>
            <gmd:userNote gco:nilReason="missing">
              <gco:CharacterString />
            </gmd:userNote>
          </gmd:MD_SecurityConstraints>
        </gmd:resourceConstraints>
        <gmd:aggregationInfo>
          <gmd:MD_AggregateInformation>
            <gmd:aggregateDataSetName>
              <gmd:CI_Citation>
                <gmd:title />
                <gmd:date />
              </gmd:CI_Citation>
            </gmd:aggregateDataSetName>
            <gmd:associationType />
          </gmd:MD_AggregateInformation>
        </gmd:aggregationInfo>
        <gmd:spatialRepresentationType>
          <gmd:MD_SpatialRepresentationTypeCode codeListValue="vector" codeList="http://standards.iso.org/ittf/PubliclyAvailableStandards/ISO_19139_Schemas/resources/codelist/ML_gmxCodelists.xml#MD_SpatialRepresentationTypeCode">vector</gmd:MD_SpatialRepresentationTypeCode>
        </gmd:spatialRepresentationType>
        <gmd:spatialResolution>
          <gmd:MD_Resolution>
            <gmd:equivalentScale>
              <gmd:MD_RepresentativeFraction>
                <gmd:denominator>
                  <gco:Integer>50000</gco:Integer>
                </gmd:denominator>
              </gmd:MD_RepresentativeFraction>
            </gmd:equivalentScale>
          </gmd:MD_Resolution>
        </gmd:spatialResolution>
        <gmd:language>
          <gmd:LanguageCode codeList="http://www.loc.gov/standards/iso639-2/" codeListValue="dut">Nederlands; Vlaams</gmd:LanguageCode>
        </gmd:language>
        <gmd:characterSet>
          <gmd:MD_CharacterSetCode codeList="http://standards.iso.org/ittf/PubliclyAvailableStandards/ISO_19139_Schemas/resources/codelist/ML_gmxCodelists.xml#MD_CharacterSetCode" codeListValue="utf8">utf8</gmd:MD_CharacterSetCode>
        </gmd:characterSet>
        <gmd:topicCategory>
          <gmd:MD_TopicCategoryCode>oceans</gmd:MD_TopicCategoryCode>
        </gmd:topicCategory>
        <gmd:extent>
          <gmd:EX_Extent>
            <gmd:description>
              <gco:CharacterString>Noordzee en binnenwater</gco:CharacterString>
            </gmd:description>
            <gmd:geographicElement>
              <gmd:EX_GeographicBoundingBox>
                <gmd:westBoundLongitude>
                  <gco:Decimal>2</gco:Decimal>
                </gmd:westBoundLongitude>
                <gmd:eastBoundLongitude>
                  <gco:Decimal>7</gco:Decimal>
                </gmd:eastBoundLongitude>
                <gmd:southBoundLatitude>
                  <gco:Decimal>51</gco:Decimal>
                </gmd:southBoundLatitude>
                <gmd:northBoundLatitude>
                  <gco:Decimal>56</gco:Decimal>
                </gmd:northBoundLatitude>
              </gmd:EX_GeographicBoundingBox>
            </gmd:geographicElement>
            <gmd:temporalElement>
              <gmd:EX_TemporalExtent>
                <gmd:extent>
                  <gml:TimePeriod gml:id="N10259">
                    <gml:beginPosition>2001-01-01</gml:beginPosition>
                    <gml:endPosition />
                  </gml:TimePeriod>
                </gmd:extent>
              </gmd:EX_TemporalExtent>
            </gmd:temporalElement>
            <gmd:verticalElement>
              <gmd:EX_VerticalExtent>
                <gmd:minimumValue />
                <gmd:maximumValue />
                <gmd:verticalCRS>
                  <gml:VerticalCRS gml:id="d18e466a1049886">
                    <gml:identifier codeSpace="" />
                    <gml:scope />
                    <gml:verticalCS />
                    <gml:verticalDatum />
                  </gml:VerticalCRS>
                </gmd:verticalCRS>
              </gmd:EX_VerticalExtent>
            </gmd:verticalElement>
          </gmd:EX_Extent>
        </gmd:extent>
      </gmd:MD_DataIdentification>
    </gmd:identificationInfo>
    <gmd:distributionInfo>
      <gmd:MD_Distribution>
        <gmd:distributionFormat />
        <gmd:distributionFormat>
          <gmd:MD_Format>
            <gmd:name>
              <gco:CharacterString>GML application schema</gco:CharacterString>
            </gmd:name>
            <gmd:version>
              <gco:CharacterString>3.2.1</gco:CharacterString>
            </gmd:version>
            <gmd:specification>
              <gco:CharacterString>D2.8.I.4 Data Specification on Administrative Units – Technical Guidelines</gco:CharacterString>
            </gmd:specification>
          </gmd:MD_Format>
        </gmd:distributionFormat>
        <gmd:distributor>
          <gmd:MD_Distributor>
            <gmd:distributorContact>
              <gmd:CI_ResponsibleParty>
                <gmd:individualName gco:nilReason="missing">
                  <gco:CharacterString />
                </gmd:individualName>
                <gmd:organisationName>
                  <gco:CharacterString>Ministerie van Defensie, Koninklijke Marine, Dienst der Hydrografie</gco:CharacterString>
                </gmd:organisationName>
                <gmd:positionName>
                  <gco:CharacterString>Hoofd Gegevens Beheer</gco:CharacterString>
                </gmd:positionName>
                <gmd:contactInfo>
                  <gmd:CI_Contact>
                    <gmd:phone>
                      <gmd:CI_Telephone>
                        <gmd:voice gco:nilReason="missing">
                          <gco:CharacterString />
                        </gmd:voice>
                        <gmd:facsimile gco:nilReason="missing">
                          <gco:CharacterString />
                        </gmd:facsimile>
                      </gmd:CI_Telephone>
                    </gmd:phone>
                    <gmd:address>
                      <gmd:CI_Address>
                        <gmd:deliveryPoint gco:nilReason="missing">
                          <gco:CharacterString />
                        </gmd:deliveryPoint>
                        <gmd:city gco:nilReason="missing">
                          <gco:CharacterString />
                        </gmd:city>
                        <gmd:administrativeArea gco:nilReason="missing">
                          <gco:CharacterString />
                        </gmd:administrativeArea>
                        <gmd:postalCode gco:nilReason="missing">
                          <gco:CharacterString />
                        </gmd:postalCode>
                        <gmd:country gco:nilReason="missing">
                          <gco:CharacterString />
                        </gmd:country>
                        <gmd:electronicMailAddress>
                          <gco:CharacterString>data@hydro.nl</gco:CharacterString>
                        </gmd:electronicMailAddress>
                      </gmd:CI_Address>
                    </gmd:address>
                    <gmd:onlineResource>
                      <gmd:CI_OnlineResource>
                        <gmd:linkage>
                          <gmd:URL>www.hydro.nl</gmd:URL>
                        </gmd:linkage>
                      </gmd:CI_OnlineResource>
                    </gmd:onlineResource>
                  </gmd:CI_Contact>
                </gmd:contactInfo>
                <gmd:role>
                  <gmd:CI_RoleCode codeList="http://standards.iso.org/ittf/PubliclyAvailableStandards/ISO_19139_Schemas/resources/codelist/ML_gmxCodelists.xml#CI_RoleCode" codeListValue="distributor">distributeur</gmd:CI_RoleCode>
                </gmd:role>
              </gmd:CI_ResponsibleParty>
            </gmd:distributorContact>
          </gmd:MD_Distributor>
        </gmd:distributor>
        <gmd:transferOptions>
          <gmd:MD_DigitalTransferOptions>
            <gmd:onLine xmlns:xlink="http://www.w3.org/1999/xlink" xmlns:java="java:org.fao.geonet.util.XslUtil">
              <gmd:CI_OnlineResource>
                <gmd:linkage>
                  <gmd:URL>https://inspire.caris.nl/geoserver/auwms/wms?request=GetCapabilities</gmd:URL>
                </gmd:linkage>
                <gmd:protocol>
                  <gmx:Anchor xlink:href="http://www.opengis.net/def/serviceType/ogc/wms">OGC:WMS</gmx:Anchor>
                </gmd:protocol>
                <gmd:applicationProfile>
                  <gmx:Anchor xlink:href="http://inspire.ec.europa.eu/metadata-codelist/SpatialDataServiceType/view">Raadpleegdienst</gmx:Anchor>
                </gmd:applicationProfile>
                <gmd:name>
                  <gco:CharacterString>AU.TerritorialSea</gco:CharacterString>
                </gmd:name>
                <gmd:description>
                  <gmx:Anchor xlink:href="http://inspire.ec.europa.eu/metadata-codelist/OnLineDescriptionCode/accessPoint">accessPoint</gmx:Anchor>
                </gmd:description>
              </gmd:CI_OnlineResource>
            </gmd:onLine>
            <gmd:onLine xmlns:xlink="http://www.w3.org/1999/xlink" xmlns:java="java:org.fao.geonet.util.XslUtil">
              <gmd:CI_OnlineResource>
                <gmd:linkage>
                  <gmd:URL>https://inspire.caris.nl/geoserver2/mu/ows?request=GetCapabilities</gmd:URL>
                </gmd:linkage>
                <gmd:protocol>
                  <gmx:Anchor xlink:href="http://www.opengis.net/def/serviceType/ogc/wfs">OGC:WFS</gmx:Anchor>
                </gmd:protocol>
                <gmd:applicationProfile>
                  <gmx:Anchor xlink:href="http://inspire.ec.europa.eu/metadata-codelist/SpatialDataServiceType/download">Downloaddienst</gmx:Anchor>
                </gmd:applicationProfile>
                <gmd:name>
                  <gco:CharacterString>MaritimeZone</gco:CharacterString>
                </gmd:name>
                <gmd:description>
                  <gmx:Anchor xlink:href="http://inspire.ec.europa.eu/metadata-codelist/OnLineDescriptionCode/accessPoint">accessPoint</gmx:Anchor>
                </gmd:description>
              </gmd:CI_OnlineResource>
            </gmd:onLine>
            <gmd:onLine xmlns:xlink="http://www.w3.org/1999/xlink" xmlns:java="java:org.fao.geonet.util.XslUtil">
              <gmd:CI_OnlineResource>
                <gmd:linkage>
                  <gmd:URL>https://inspire.caris.nl/atom/maritieme-grenzen-zones-noordzee-Territoriale-Zee-Noordzee-feed.atom</gmd:URL>
                </gmd:linkage>
                <gmd:protocol>
                  <gmx:Anchor xlink:href="https://tools.ietf.org/html/rfc4287">INSPIRE Atom</gmx:Anchor>
                </gmd:protocol>
                <gmd:name>
                  <gco:CharacterString>Territoriale Zee volgens UNCLOS - Noordzee - ATOM</gco:CharacterString>
                </gmd:name>
                <gmd:description>
                  <gmx:Anchor xlink:href="http://inspire.ec.europa.eu/metadata-codelist/OnLineDescriptionCode/accessPoint">accessPoint</gmx:Anchor>
                </gmd:description>
              </gmd:CI_OnlineResource>
            </gmd:onLine>
            <gmd:offLine>
              <gmd:MD_Medium>
                <gmd:name>
                  <gmd:MD_MediumNameCode codeList="http://standards.iso.org/ittf/PubliclyAvailableStandards/ISO_19139_Schemas/resources/codelist/ML_gmxCodelists.xml#MD_MediumNameCode" codeListValue="dvd">dvd</gmd:MD_MediumNameCode>
                </gmd:name>
              </gmd:MD_Medium>
            </gmd:offLine>
          </gmd:MD_DigitalTransferOptions>
        </gmd:transferOptions>
      </gmd:MD_Distribution>
    </gmd:distributionInfo>
    <gmd:dataQualityInfo>
      <gmd:DQ_DataQuality>
        <gmd:scope>
          <gmd:DQ_Scope>
            <gmd:level>
              <gmd:MD_ScopeCode codeListValue="dataset" codeList="http://standards.iso.org/ittf/PubliclyAvailableStandards/ISO_19139_Schemas/resources/codelist/ML_gmxCodelists.xml#MD_ScopeCode">dataset</gmd:MD_ScopeCode>
            </gmd:level>
          </gmd:DQ_Scope>
        </gmd:scope>
        <gmd:report>
          <gmd:DQ_AbsoluteExternalPositionalAccuracy>
            <gmd:result>
              <gmd:DQ_QuantitativeResult>
                <gmd:valueUnit>
                  <gml:BaseUnit gml:id="N1042F">
                    <gml:identifier codeSpace="" />
                    <gml:unitsSystem />
                  </gml:BaseUnit>
                </gmd:valueUnit>
                <gmd:value />
              </gmd:DQ_QuantitativeResult>
            </gmd:result>
          </gmd:DQ_AbsoluteExternalPositionalAccuracy>
        </gmd:report>
        <gmd:report>
          <gmd:DQ_CompletenessOmission>
            <gmd:result>
              <gmd:DQ_QuantitativeResult>
                <gmd:valueUnit>
                  <gml:BaseUnit gml:id="d18e663a1049886">
                    <gml:identifier codeSpace="" />
                    <gml:unitsSystem />
                  </gml:BaseUnit>
                </gmd:valueUnit>
                <gmd:value />
              </gmd:DQ_QuantitativeResult>
            </gmd:result>
          </gmd:DQ_CompletenessOmission>
        </gmd:report>
        <gmd:report>
          <gmd:DQ_DomainConsistency>
            <gmd:result>
              <gmd:DQ_ConformanceResult>
                <gmd:specification>
                  <gmd:CI_Citation>
                    <gmd:title>
                      <gco:CharacterString>VERORDENING (EU) Nr. 1089/2010 VAN DE COMMISSIE van 23 november 2010 ter uitvoering van Richtlijn 2007/2/EG van het Europees Parlement en de Raad betreffende de interoperabiliteit van verzamelingen ruimtelijke gegevens en van diensten met betrekking tot ruimtelijke gegevens</gco:CharacterString>
                    </gmd:title>
                    <gmd:date>
                      <gmd:CI_Date>
                        <gmd:date>
                          <gco:Date>2010-12-08</gco:Date>
                        </gmd:date>
                        <gmd:dateType>
                          <gmd:CI_DateTypeCode codeList="http://standards.iso.org/ittf/PubliclyAvailableStandards/ISO_19139_Schemas/resources/codelist/ML_gmxCodelists.xml#CI_DateTypeCode" codeListValue="publication">publicatie</gmd:CI_DateTypeCode>
                        </gmd:dateType>
                      </gmd:CI_Date>
                    </gmd:date>
                  </gmd:CI_Citation>
                </gmd:specification>
                <gmd:explanation>
                  <gco:CharacterString>Dataset is geharmoniseerd</gco:CharacterString>
                </gmd:explanation>
                <gmd:pass>
                  <gco:Boolean>true</gco:Boolean>
                </gmd:pass>
              </gmd:DQ_ConformanceResult>
            </gmd:result>
          </gmd:DQ_DomainConsistency>
        </gmd:report>
        <gmd:report>
          <gmd:DQ_TopologicalConsistency>
            <gmd:result>
              <gmd:DQ_QuantitativeResult>
                <gmd:valueUnit>
                  <gml:BaseUnit gml:id="d18e672a1049886">
                    <gml:identifier codeSpace="" />
                    <gml:unitsSystem />
                  </gml:BaseUnit>
                </gmd:valueUnit>
                <gmd:value />
              </gmd:DQ_QuantitativeResult>
            </gmd:result>
          </gmd:DQ_TopologicalConsistency>
        </gmd:report>
        <gmd:lineage>
          <gmd:LI_Lineage>
            <gmd:statement>
              <gco:CharacterString>Dienst der Hydrografie, Rijkswaterstaat en andere hydrografische bronnen, Grensverdrag tussen Nederland en België, Grensverdrag tussen Nederland en Duitsland, Grensverdrag tussen Nederland en het Verenigd Koninkrijk, Besluit instelling Aansluitende Zone in Nederland.</gco:CharacterString>
            </gmd:statement>
            <gmd:processStep>
              <gmd:LI_ProcessStep>
                <gmd:description>
                  <gco:CharacterString>Analyse en kwaliteitscontrole</gco:CharacterString>
                </gmd:description>
                <gmd:processor>
                  <gmd:CI_ResponsibleParty>
                    <gmd:organisationName />
                    <gmd:contactInfo>
                      <gmd:CI_Contact>
                        <gmd:address>
                          <gmd:CI_Address>
                            <gmd:electronicMailAddress gco:nilReason="missing">
                              <gco:CharacterString />
                            </gmd:electronicMailAddress>
                          </gmd:CI_Address>
                        </gmd:address>
                      </gmd:CI_Contact>
                    </gmd:contactInfo>
                    <gmd:role>
                      <gmd:CI_RoleCode codeList="http://standards.iso.org/ittf/PubliclyAvailableStandards/ISO_19139_Schemas/resources/codelist/ML_gmxCodelists.xml#CI_RoleCode" codeListValue="processor">bewerker</gmd:CI_RoleCode>
                    </gmd:role>
                  </gmd:CI_ResponsibleParty>
                </gmd:processor>
              </gmd:LI_ProcessStep>
            </gmd:processStep>
            <gmd:source>
              <gmd:LI_Source>
                <gmd:sourceStep>
                  <gmd:LI_ProcessStep>
                    <gmd:description />
                    <gmd:processor>
                      <gmd:CI_ResponsibleParty>
                        <gmd:organisationName />
                        <gmd:contactInfo>
                          <gmd:CI_Contact>
                            <gmd:address>
                              <gmd:CI_Address>
                                <gmd:electronicMailAddress gco:nilReason="missing">
                                  <gco:CharacterString />
                                </gmd:electronicMailAddress>
                              </gmd:CI_Address>
                            </gmd:address>
                          </gmd:CI_Contact>
                        </gmd:contactInfo>
                        <gmd:role />
                      </gmd:CI_ResponsibleParty>
                    </gmd:processor>
                  </gmd:LI_ProcessStep>
                </gmd:sourceStep>
              </gmd:LI_Source>
            </gmd:source>
          </gmd:LI_Lineage>
        </gmd:lineage>
      </gmd:DQ_DataQuality>
    </gmd:dataQualityInfo>
    <gmd:dataQualityInfo>
      <gmd:DQ_DataQuality>
        <gmd:scope>
          <gmd:DQ_Scope>
            <gmd:level>
              <gmd:MD_ScopeCode codeListValue="dataset" codeList="http://standards.iso.org/ittf/PubliclyAvailableStandards/ISO_19139_Schemas/resources/codelist/ML_gmxCodelists.xml#MD_ScopeCode">dataset</gmd:MD_ScopeCode>
            </gmd:level>
          </gmd:DQ_Scope>
        </gmd:scope>
        <gmd:report>
          <gmd:DQ_DomainConsistency>
            <gmd:result>
              <gmd:DQ_ConformanceResult>
                <gmd:specification>
                  <gmd:CI_Citation>
                    <gmd:title>
                      <gco:CharacterString>INSPIRE Data Specification on Administrative Units - Guidelines v3.0.1</gco:CharacterString>
                    </gmd:title>
                    <gmd:date>
                      <gmd:CI_Date>
                        <gmd:date>
                          <gco:Date>2010-05-03</gco:Date>
                        </gmd:date>
                        <gmd:dateType>
                          <gmd:CI_DateTypeCode codeList="http://standards.iso.org/ittf/PubliclyAvailableStandards/ISO_19139_Schemas/resources/codelist/ML_gmxCodelists.xml#CI_DateTypeCode" codeListValue="publication">publicatie</gmd:CI_DateTypeCode>
                        </gmd:dateType>
                      </gmd:CI_Date>
                    </gmd:date>
                  </gmd:CI_Citation>
                </gmd:specification>
                <gmd:explanation>
                  <gco:CharacterString>See the referenced specification</gco:CharacterString>
                </gmd:explanation>
                <gmd:pass>
                  <gco:Boolean>true</gco:Boolean>
                </gmd:pass>
              </gmd:DQ_ConformanceResult>
            </gmd:result>
          </gmd:DQ_DomainConsistency>
        </gmd:report>
      </gmd:DQ_DataQuality>
    </gmd:dataQualityInfo>
    <gmd:dataQualityInfo>
      <gmd:DQ_DataQuality>
        <gmd:scope>
          <gmd:DQ_Scope>
            <gmd:level>
              <gmd:MD_ScopeCode codeListValue="dataset" codeList="http://standards.iso.org/ittf/PubliclyAvailableStandards/ISO_19139_Schemas/resources/codelist/ML_gmxCodelists.xml#MD_ScopeCode">dataset</gmd:MD_ScopeCode>
            </gmd:level>
          </gmd:DQ_Scope>
        </gmd:scope>
        <gmd:report>
          <gmd:DQ_DomainConsistency>
            <gmd:result>
              <gmd:DQ_ConformanceResult>
                <gmd:specification>
                  <gmd:CI_Citation>
                    <gmd:title>
                      <gco:CharacterString>COMMISSION REGULATION (EU) No 1089/2010 of 23 November 2010 implementing Directive 2007/2/EC of the European Parliament and of the Council as regards interoperability of spatial data sets and services</gco:CharacterString>
                    </gmd:title>
                    <gmd:date>
                      <gmd:CI_Date>
                        <gmd:date>
                          <gco:Date>2010-12-08</gco:Date>
                        </gmd:date>
                        <gmd:dateType>
                          <gmd:CI_DateTypeCode codeList="http://standards.iso.org/ittf/PubliclyAvailableStandards/ISO_19139_Schemas/resources/codelist/ML_gmxCodelists.xml#CI_DateTypeCode" codeListValue="publication">publicatie</gmd:CI_DateTypeCode>
                        </gmd:dateType>
                      </gmd:CI_Date>
                    </gmd:date>
                  </gmd:CI_Citation>
                </gmd:specification>
                <gmd:explanation>
                  <gco:CharacterString>See the referenced specification</gco:CharacterString>
                </gmd:explanation>
                <gmd:pass>
                  <gco:Boolean>true</gco:Boolean>
                </gmd:pass>
              </gmd:DQ_ConformanceResult>
            </gmd:result>
          </gmd:DQ_DomainConsistency>
        </gmd:report>
      </gmd:DQ_DataQuality>
    </gmd:dataQualityInfo>
  </gmd:MD_Metadata>
</csw:GetRecordByIdResponse>

